RSA.py
bf.py
cc.py
dfh.py
vc.py
ceaser-1.0.0.dist-info/METADATA
ceaser-1.0.0.dist-info/WHEEL
ceaser-1.0.0.dist-info/top_level.txt
ceaser-1.0.0.dist-info/RECORD
