Metadata-Version: 2.1
Name: ceaser
Version: 1.0.0
Summary: Hackcode
Home-page: UNKNOWN
Author: Gandu
Author-email: gandu@hotmail.com
License: UNKNOWN
Platform: UNKNOWN
